<?xml version="1.0" encoding="UTF-8"?>
<objects serializationModel="Studio.02.02.00">
	<object class="AudioFile" id="{9f1781e5-8134-4b56-84a5-7cdcce49611b}">
		<property name="assetPath">
			<value>345066__metrostock99__car-door-closing-from-inside.wav</value>
		</property>
		<property name="frequencyInKHz">
			<value>44.0999985</value>
		</property>
		<property name="channelCount">
			<value>2</value>
		</property>
		<property name="length">
			<value>1.6291156462585035</value>
		</property>
		<relationship name="masterAssetFolder">
			<destination>{48102138-9dc2-4e11-a962-9be4d9ea37bc}</destination>
		</relationship>
	</object>
</objects>
